CHANGES.txt
README.txt
assumptions.txt
bootstrap.py
buildout.cfg
design.txt
sample-project.xml
setup.py
src/z3c/__init__.py
src/z3c.builder.core.egg-info/PKG-INFO
src/z3c.builder.core.egg-info/SOURCES.txt
src/z3c.builder.core.egg-info/dependency_links.txt
src/z3c.builder.core.egg-info/namespace_packages.txt
src/z3c.builder.core.egg-info/not-zip-safe
src/z3c.builder.core.egg-info/requires.txt
src/z3c.builder.core.egg-info/top_level.txt
src/z3c/builder/__init__.py
src/z3c/builder/core/README.txt
src/z3c/builder/core/__init__.py
src/z3c/builder/core/base.py
src/z3c/builder/core/buildout.py
src/z3c/builder/core/buildout.txt
src/z3c/builder/core/class-diagram.dot
src/z3c/builder/core/class-diagram.png
src/z3c/builder/core/example.txt
src/z3c/builder/core/form.py
src/z3c/builder/core/form.txt
src/z3c/builder/core/index.txt
src/z3c/builder/core/interfaces.py
src/z3c/builder/core/project.py
src/z3c/builder/core/project.txt
src/z3c/builder/core/python.py
src/z3c/builder/core/python.txt
src/z3c/builder/core/setup.py
src/z3c/builder/core/setup.txt
src/z3c/builder/core/testing.py
src/z3c/builder/core/trove-classifiers.txt
src/z3c/builder/core/zcml.py
src/z3c/builder/core/zcml.txt
src/z3c/builder/core/file-templates/__init__.py
src/z3c/builder/core/file-templates/__init__namespace.py
src/z3c/builder/core/file-templates/add-form.py
src/z3c/builder/core/file-templates/bootstrap.py
src/z3c/builder/core/file-templates/buildout.cfg
src/z3c/builder/core/file-templates/edit-form.py
src/z3c/builder/core/file-templates/gpl3-header.py
src/z3c/builder/core/file-templates/proprietary-header.py
src/z3c/builder/core/file-templates/setup.py
src/z3c/builder/core/file-templates/simple-display-form.pt
src/z3c/builder/core/file-templates/simple-display-form.py
src/z3c/builder/core/file-templates/zboiler-doc-header.txt
src/z3c/builder/core/file-templates/zpl-header.py
src/z3c/builder/core/tests/__init__.py
src/z3c/builder/core/tests/test_doc.py