Metadata-Version: 1.0
Name: z3c.builder.core
Version: 0.1.0
Summary: A utility to help jump start Zope 3 projects
Home-page: http://pypi.python.org/pypi/z3c.builder.core
Author: Paul Carduner, Stephan Richter, and hopefully others...
Author-email: zope-dev@zope.org
License: ZPL 2.1
Keywords: zope3 project builder
Platform: UNKNOWN
